sqlalchemy_faker/__init__.py
sqlalchemy_faker/core.py
sqlalchemy_faker-0.0.4.dist-info/LICENSE.txt
sqlalchemy_faker-0.0.4.dist-info/METADATA
sqlalchemy_faker-0.0.4.dist-info/WHEEL
sqlalchemy_faker-0.0.4.dist-info/top_level.txt
sqlalchemy_faker-0.0.4.dist-info/RECORD
