Metadata-Version: 2.1
Name: sqlalchemy-faker
Version: 0.0.4
Summary: a tool of sqlalchemy for generating fake data
Home-page: https://github.com/GongSakura/SQLAlchemy-Faker
Author: GongSakura
Author-email: gongskaura@yahoo.com
License: UNKNOWN
Platform: UNKNOWN
Classifier: Programming Language :: Python :: 3
Classifier: License :: OSI Approved :: MIT License
Classifier: Operating System :: OS Independent
Requires-Python: >=3.6
License-File: LICENSE.txt
